{
  "tags": [
    {
      "name": "release",
      "version": "0.9.7",
      "commit": "fe19cbb",
      "upstream": "Releases",
      "lastUpdated": "2021-08-13T22:18:04.955Z"
    },
    {
      "name": "testing",
      "version": "",
      "commit": "",
      "upstream": "",
      "lastUpdated": ""
    },
    {
      "name": "nightly",
      "version": "0.9.7",
      "commit": "2892e61",
      "upstream": "Pre-releases",
      "lastUpdated": "2021-08-13T12:17:41.926Z"
    }
  ],
  "pulls": 10675034,
  "stars": 13
}
